sassy/__init__.py
sassy/error.py
sassy/interpreter.py
sassy/parser.py
sassy/scanner.py
sassy/token.py
sassy/tokentype.py
sassy/translator.py
sassylang-0.0.5.dist-info/LICENSE
sassylang-0.0.5.dist-info/METADATA
sassylang-0.0.5.dist-info/WHEEL
sassylang-0.0.5.dist-info/entry_points.txt
sassylang-0.0.5.dist-info/top_level.txt
sassylang-0.0.5.dist-info/RECORD
