Metadata-Version: 2.1
Name: sassylang
Version: 0.0.5
Summary: A simple but powerful templating language for text interpolation inspired by sas macros.
Home-page: https://github.com/jmsmistral/sassy
Author: Jonathan Sacramento
Author-email: jmsmistral@gmail.com
License: UNKNOWN
Keywords: templates macros text interpolation sas
Platform: UNKNOWN
Classifier: Development Status :: 3 - Alpha
Classifier: Intended Audience :: Developers
Classifier: License :: OSI Approved :: GNU General Public License v3 or later (GPLv3+)
Classifier: Programming Language :: Python :: 3.6
Requires-Dist: docopt
